SpeechFast/__init__.py
SpeechFast/converter.py
SpeechFast/punctuator.py
SpeechFast/recognizer.py
SpeechFast-0.2.9.1.dist-info/LICENSE
SpeechFast-0.2.9.1.dist-info/METADATA
SpeechFast-0.2.9.1.dist-info/WHEEL
SpeechFast-0.2.9.1.dist-info/top_level.txt
SpeechFast-0.2.9.1.dist-info/RECORD
