Metadata-Version: 2.1
Name: SpeechFast
Version: 0.2.9.1
Summary: Transcriber audio/video to text
Home-page: https://github.com/imdevok/speechfast
Author: imdevok
Author-email: <lenyamenshov@yandex.ru>
License: UNKNOWN
Keywords: python,video,text,speech,audio,AI
Platform: UNKNOWN
Classifier: Development Status :: 1 - Planning
Classifier: Intended Audience :: Developers
Classifier: Programming Language :: Python :: 3
Classifier: Operating System :: Unix
Classifier: Operating System :: MacOS :: MacOS X
Classifier: Operating System :: Microsoft :: Windows
License-File: LICENSE
Requires-Dist: vosk
Requires-Dist: torch
Requires-Dist: pyyaml
Requires-Dist: numpy
